{
  "type": "FREE_CODING",
  "id": "epoch-1-lesson-5-simple",
  "title": "Create a Simple Method",
  "description": "Create a method called 'printWelcome' that prints \"Welcome!\"\n\nThe method should:\n- Return void (nothing)\n- Have no parameters\n- Print: Welcome!\n\nThen call it from main.\n\nExpected output: Welcome!",
  "instructions": "Create a method called 'printWelcome' that prints \"Welcome!\"\n\nThe method should:\n- Return void (nothing)\n- Have no parameters\n- Print: Welcome!\n\nThen call it from main.\n\nExpected output: Welcome!",
  "language": "java",
  "testCases": [
    {
      "id": "epoch-1-lesson-5-simple-test-1",
      "description": "Should print Welcome!",
      "expectedOutput": "Welcome!",
      "isVisible": true
    }
  ],
  "hints": [
    {
      "level": 1,
      "text": "Use IO.println() to display output to the console."
    },
    {
      "level": 2,
      "text": "Define a function using the java syntax. Don't forget the return statement if needed."
    },
    {
      "level": 3,
      "text": "If stuck, try writing out the solution in plain English first, then convert to java code."
    }
  ],
  "commonMistakes": [
    {
      "mistake": "Forgetting semicolons",
      "consequence": "Compilation error",
      "correction": "Add ; at end of statements"
    },
    {
      "mistake": "Using = instead of == for comparison",
      "consequence": "Assignment instead of comparison",
      "correction": "Use == for primitives, .equals() for objects"
    },
    {
      "mistake": "Incorrect capitalization (Java is case-sensitive)",
      "consequence": "Cannot find symbol error",
      "correction": "Match exact capitalization"
    }
  ],
  "difficulty": "beginner"
}