{
  "type": "FREE_CODING",
  "id": "3.3-challenge",
  "title": "Practice Challenge",
  "description": "Create a simple login validator:\n1. Create two variables: 'password' (a string) and 'confirmPassword' (another string)\n2. If they are equal (===), display 'Passwords match!'\n3. If they are not equal (!==), display 'Passwords do not match'",
  "instructions": "Create a simple login validator:\n1. Create two variables: 'password' (a string) and 'confirmPassword' (another string)\n2. If they are equal (===), display 'Passwords match!'\n3. If they are not equal (!==), display 'Passwords do not match'",
  "language": "javascript",
  "testCases": [
    {
      "id": "test-1",
      "description": "Detects matching passwords",
      "expectedOutput": "Passwords match!",
      "isVisible": true
    }
  ],
  "hints": [
    {
      "level": 1,
      "text": "Use === to check if they're equal: if (password === confirmPassword)"
    }
  ],
  "commonMistakes": [
    {
      "mistake": "Common mistakes:",
      "consequence": "This can lead to errors or unexpected behavior.",
      "correction": "Common mistakes:"
    },
    {
      "mistake": "Using = instead of ===:",
      "consequence": "This can lead to errors or unexpected behavior.",
      "correction": "Using = instead of ===:\n   if (age = 18)  // WRONG - this assigns 18 to age!\n   if (age === 18)  // CORRECT - this compares"
    },
    {
      "mistake": "Using == instead of ===:",
      "consequence": "This can lead to errors or unexpected behavior.",
      "correction": "Using == instead of ===:\n   JavaScript has == (loose equality) and === (strict equality)\n   - 5 == '5' → true (converts types, then compares)\n   - 5 === '5' → false (different types)\n   ALWAYS use === and !== to avoid surprises"
    }
  ],
  "difficulty": "beginner"
}