{
  "type": "FREE_CODING",
  "id": "lesson-02-05-challenge-01",
  "title": "Practice Challenge",
  "description": "Apply what you've learned in this interactive coding challenge.",
  "instructions": "Create a game level-up simulator!\n\n1. Start with: level = 1, experience = 0, coins = 100\n2. Gain 50 experience (use +=)\n3. Level up by 1 (use ++)\n4. Double your coins (use *=)\n5. Spend 25 coins (use -=)\n6. Display level, experience, and coins after each change!",
  "language": "csharp",
  "testCases": [
    {
      "id": "test-1",
      "description": "Output should contain \"Level\"",
      "expectedOutput": "Level",
      "isVisible": true
    },
    {
      "id": "test-2",
      "description": "Output should contain \"XP\"",
      "expectedOutput": "XP",
      "isVisible": true
    },
    {
      "id": "test-3",
      "description": "Output should contain \"Coins\"",
      "expectedOutput": "Coins",
      "isVisible": true
    }
  ],
  "hints": [
    {
      "level": 1,
      "text": "Use +=, -=, *=, and ++ operators! experience += 50 adds to experience, level++ increases by 1, coins *= 2 doubles coins, coins -= 25 subtracts!"
    },
    {
      "level": 2,
      "text": "Forgetting that score++ changes the variable permanently! It's not temporary – score is now 1 higher."
    },
    {
      "level": 3,
      "text": "Trying to use ++ with non-numeric types: name++ doesn't make sense! You can only increment numbers."
    },
    {
      "level": 4,
      "text": "Confusing score += 5 with score = 5: The first ADDS 5, the second REPLACES with 5!"
    }
  ],
  "commonMistakes": [
    {
      "mistake": "Forgetting that score++ changes the variable permanently! It's not temporary – score is now 1 higher.",
      "consequence": "This is a common error that can cause problems.",
      "correction": "Review the lesson content and examples carefully."
    },
    {
      "mistake": "Trying to use ++ with non-numeric types",
      "consequence": "name++ doesn't make sense! You can only increment numbers.",
      "correction": "Review the correct syntax and best practices for this concept."
    },
    {
      "mistake": "Confusing score += 5 with score = 5",
      "consequence": "The first ADDS 5, the second REPLACES with 5!",
      "correction": "Review the correct syntax and best practices for this concept."
    }
  ],
  "difficulty": "beginner"
}