{
  "id": "lesson-21-05",
  "title": "Session-Based vs Token-Based Auth",
  "moduleId": "module-21",
  "order": 5,
  "estimatedMinutes": 40,
  "difficulty": "advanced",
  "tags": [
    "authentication",
    "sessions",
    "tokens",
    "jwt",
    "redis",
    "security"
  ],
  "learningObjectives": [
    "Understand session-based authentication architecture",
    "Understand token-based authentication architecture",
    "Compare when to use sessions vs tokens",
    "Implement session storage with Redis"
  ]
}
